argparse_decorations/__init__.py
argparse_decorations-0.0.1.dist-info/METADATA
argparse_decorations-0.0.1.dist-info/WHEEL
argparse_decorations-0.0.1.dist-info/top_level.txt
argparse_decorations-0.0.1.dist-info/RECORD
