Metadata-Version: 2.1
Name: argparse-decorations
Version: 0.0.1
Summary: argparse wrapper around decorations
Home-page: https://bitbucket.org/rmonico/argparse_decorations
Author: Rafael Monico
Author-email: rmonico1@gmail.com
License: GPL3
